cfy/__init__.py
cfy/py.typed
cfy/cli/__init__.py
cfy/cli/commands.py
cfy/cli/parser.py
cfy/core/__init__.py
cfy/core/base.py
cfy/core/exceptions.py
cfy/core/loader.py
cfy/core/sources.py
cfy/formats/__init__.py
cfy/formats/base.py
cfy/formats/json_format.py
cfy/formats/toml_format.py
cfy/formats/yaml_format.py
cfy/integrations/__init__.py
cfy/integrations/fastapi.py
cfy/security/__init__.py
cfy/security/secrets.py
cfy/utils/__init__.py
cfy/utils/interpolation.py
cfy/utils/performance.py
cfy-0.1.0.post13.dist-info/METADATA
cfy-0.1.0.post13.dist-info/WHEEL
cfy-0.1.0.post13.dist-info/entry_points.txt
cfy-0.1.0.post13.dist-info/RECORD
