Metadata-Version: 2.4
Name: cfy
Version: 0.1.0.post13
Summary: Modern Python configuration management system with CLI override support
Project-URL: Homepage, https://github.com/JAMESVEITCH/cfy
Project-URL: Documentation, https://github.com/JAMESVEITCH/cfy#readme
Project-URL: Source, https://github.com/JAMESVEITCH/cfy
Project-URL: Issues, https://github.com/JAMESVEITCH/cfy/issues
Author-email: James Veitch <james@example.com>
License: MIT
Keywords: cli,configuration,environment,fastapi,pydantic,settings
Classifier: Development Status :: 4 - Beta
Classifier: Framework :: FastAPI
Classifier: Framework :: Pydantic
Classifier: Intended Audience :: Developers
Classifier: License :: OSI Approved :: MIT License
Classifier: Programming Language :: Python :: 3
Classifier: Programming Language :: Python :: 3.12
Classifier: Topic :: Software Development :: Libraries :: Python Modules
Requires-Python: >=3.12
Requires-Dist: fastapi>=0.116.1
Requires-Dist: pydantic-settings>=2.1.0
Requires-Dist: pydantic>=2.5.0
Requires-Dist: python-dotenv>=1.0.0
Requires-Dist: pyyaml>=6.0.1
Requires-Dist: rich>=13.7.0
Requires-Dist: tomli-w>=1.0.0
Requires-Dist: typer>=0.9.0
Provides-Extra: dev
Requires-Dist: asyncpg>=0.29.0; extra == 'dev'
Requires-Dist: black>=23.12.1; extra == 'dev'
Requires-Dist: fastapi>=0.109.0; extra == 'dev'
Requires-Dist: fastapi>=0.116.1; extra == 'dev'
Requires-Dist: httpx>=0.26.0; extra == 'dev'
Requires-Dist: hypothesis>=6.92.0; extra == 'dev'
Requires-Dist: ipython>=8.19.0; extra == 'dev'
Requires-Dist: mypy>=1.8.0; extra == 'dev'
Requires-Dist: pre-commit>=3.6.0; extra == 'dev'
Requires-Dist: pytest-asyncio>=0.21.1; extra == 'dev'
Requires-Dist: pytest-cov>=4.1.0; extra == 'dev'
Requires-Dist: pytest>=7.4.4; extra == 'dev'
Requires-Dist: redis>=5.0.0; extra == 'dev'
Requires-Dist: ruff>=0.1.11; extra == 'dev'
Requires-Dist: uvicorn[standard]>=0.27.0; extra == 'dev'
Provides-Extra: examples
Requires-Dist: ipykernel>=6.30.1; extra == 'examples'
Requires-Dist: pip>=25.2; extra == 'examples'
Provides-Extra: fastapi
Requires-Dist: asyncpg>=0.29.0; extra == 'fastapi'
Requires-Dist: fastapi>=0.109.0; extra == 'fastapi'
Requires-Dist: redis>=5.0.0; extra == 'fastapi'
Requires-Dist: uvicorn[standard]>=0.27.0; extra == 'fastapi'
Provides-Extra: test
Requires-Dist: fastapi>=0.116.1; extra == 'test'
Requires-Dist: httpx>=0.26.0; extra == 'test'
Requires-Dist: hypothesis>=6.92.0; extra == 'test'
Requires-Dist: pytest-asyncio>=0.21.1; extra == 'test'
Requires-Dist: pytest-cov>=4.1.0; extra == 'test'
Requires-Dist: pytest>=7.4.4; extra == 'test'
